SidraDataProductSDK/__init__.py
SidraDataProductSDK/api_client.py
SidraDataProductSDK/configuration.py
SidraDataProductSDK/rest.py
SidraDataProductSDK/api/__init__.py
SidraDataProductSDK/api/asset_api.py
SidraDataProductSDK/api/azure_search_api.py
SidraDataProductSDK/api/configuration_api.py
SidraDataProductSDK/api/data_source_api.py
SidraDataProductSDK/api/group_api.py
SidraDataProductSDK/api/model_api.py
SidraDataProductSDK/api/pipeline_api.py
SidraDataProductSDK/api/refresh_api.py
SidraDataProductSDK/api/role_member_api.py
SidraDataProductSDK/api/staging_configuration_api.py
SidraDataProductSDK/api/status_api.py
SidraDataProductSDK/api/sync_api.py
SidraDataProductSDK/api/validation_api.py
SidraDataProductSDK/models/__init__.py
SidraDataProductSDK/models/analyzer.py
SidraDataProductSDK/models/analyzer_name.py
SidraDataProductSDK/models/asset_dto.py
SidraDataProductSDK/models/asset_status_enum.py
SidraDataProductSDK/models/asset_status_request.py
SidraDataProductSDK/models/asset_time_travel_dto.py
SidraDataProductSDK/models/asset_time_travel_full_dto.py
SidraDataProductSDK/models/asset_time_travel_item_dto.py
SidraDataProductSDK/models/base_search_service_request.py
SidraDataProductSDK/models/char_filter.py
SidraDataProductSDK/models/check_process_dto.py
SidraDataProductSDK/models/cognitive_services.py
SidraDataProductSDK/models/consolidation_modes.py
SidraDataProductSDK/models/cors_options.py
SidraDataProductSDK/models/data_change_detection_policy.py
SidraDataProductSDK/models/data_container.py
SidraDataProductSDK/models/data_deletion_detection_policy.py
SidraDataProductSDK/models/data_source.py
SidraDataProductSDK/models/data_source_credentials.py
SidraDataProductSDK/models/data_source_parameter_request.py
SidraDataProductSDK/models/data_source_parameter_response.py
SidraDataProductSDK/models/data_source_request.py
SidraDataProductSDK/models/data_source_type.py
SidraDataProductSDK/models/data_type.py
SidraDataProductSDK/models/entity_pipeline_dto.py
SidraDataProductSDK-2025.8.1.post180.dist-info/METADATA
SidraDataProductSDK-2025.8.1.post180.dist-info/WHEEL
SidraDataProductSDK-2025.8.1.post180.dist-info/top_level.txt
SidraDataProductSDK-2025.8.1.post180.dist-info/RECORD
