Metadata-Version: 2.1
Name: SidraDataProductSDK
Version: 2025.8.1.post180
Summary: Sidra App SDK
Home-page: 
Author-email: info@sidra.dev
Keywords: Swagger,Sidra App SDK
Requires-Dist: certifi
Requires-Dist: python-dateutil
Requires-Dist: six >=1.10
Requires-Dist: urllib3 >=1.15
